walytis_identities/__init__.py
walytis_identities/datatransmission.py
walytis_identities/did_manager.py
walytis_identities/did_manager_blocks.py
walytis_identities/did_manager_with_supers.py
walytis_identities/exceptions.py
walytis_identities/generic_did_manager.py
walytis_identities/generics.py
walytis_identities/group_did_manager.py
walytis_identities/key_objects.py
walytis_identities/key_store.py
walytis_identities/log.py
walytis_identities/settings.py
walytis_identities/utils.py
walytis_identities-0.5.0.dist-info/licenses/LICENSE
walytis_identities-0.5.0.dist-info/licenses/LICENSE-CC0
walytis_identities-0.5.0.dist-info/METADATA
walytis_identities-0.5.0.dist-info/WHEEL
walytis_identities-0.5.0.dist-info/top_level.txt
walytis_identities-0.5.0.dist-info/RECORD
