Metadata-Version: 2.4
Name: walytis_identities
Version: 0.5.0
Summary: A system for managing identities, contacts and their cryptographic keys based on the Walytis blockchain.
Author: emendir
Requires-Python: >=3.10
License-File: LICENSE
License-File: LICENSE-CC0
Requires-Dist: rfc3987
Requires-Dist: walytis_beta_api>=2.4.16
Requires-Dist: walytis_beta_embedded>=0.0.13
Requires-Dist: decorate_all
Requires-Dist: py_strict_typing
Requires-Dist: loguru
Requires-Dist: portalocker
Requires-Dist: multi_crypt>=0.1.3
Requires-Dist: dataclasses_json
Requires-Dist: emtest>=0.0.5
Dynamic: license-file
